setup.py
TzaraIPA.egg-info/PKG-INFO
TzaraIPA.egg-info/SOURCES.txt
TzaraIPA.egg-info/dependency_links.txt
TzaraIPA.egg-info/top_level.txt
bin/startup.sh
tzara/Speech.py
tzara/__init__.py
tzara/confirm.py
tzara/converse.py
tzara/database.py
tzara/files.py
tzara/firefox.py
tzara/main.py
tzara/pdf.py
tzara/playmovie.py
tzara/reminder.py
tzara/songs.py
tzara/terminal.py
tzara/tzara.py