Metadata-Version: 1.0
Name: TzaraIPA
Version: 0.1
Summary: A Virtual Personal Assistant
Home-page: https://github.com/Suman7495/Tzara---A-Personal-Assistant
Author: Suman Pal
Author-email: suman7495@gmail.com
License: MIT
Platform: UNKNOWN
